iq_gen-0.1.1.dist-info/METADATA
iq_gen-0.1.1.dist-info/WHEEL
iq_gen/__init__.py
iq_gen-0.1.1.dist-info/RECORD
