Metadata-Version: 2.1
Name: IQ-gen
Version: 0.1.1
Summary: Default template for PDM package
Author: jnnchi, Max, gabe, Toyakki
License: MIT
Requires-Python: >=3.11
Requires-Dist: Flask
Requires-Dist: openai
Requires-Dist: subprocess
Requires-Dist: dotenv
